[
  {
    "route": "/",
    "firstLoadUncompressedJsBytes": 844480,
    "firstLoadChunkPaths": [
      ".next/static/chunks/1658s.jmfu3bl.js",
      ".next/static/chunks/0~xsfa46ru.-w.js",
      ".next/static/chunks/0-cre2cv4mczu.js",
      ".next/static/chunks/04nob3q2ijusp.js",
      ".next/static/chunks/0pnhx35pwaxvd.js",
      ".next/static/chunks/0a3nm8r6kmyn3.js",
      ".next/static/chunks/0jvyaixqsz1ap.js",
      ".next/static/chunks/0fjlk3~at3w55.js",
      ".next/static/chunks/14s.rtfgouzu..js",
      ".next/static/chunks/turbopack-05vf~d5vj8vz_.js"
    ]
  },
  {
    "route": "/customers/[id]",
    "firstLoadUncompressedJsBytes": 808102,
    "firstLoadChunkPaths": [
      ".next/static/chunks/1658s.jmfu3bl.js",
      ".next/static/chunks/0~xsfa46ru.-w.js",
      ".next/static/chunks/0ed.2vkpqlpi1.js",
      ".next/static/chunks/0_t7vr6-missb.js",
      ".next/static/chunks/0a3nm8r6kmyn3.js",
      ".next/static/chunks/0jvyaixqsz1ap.js",
      ".next/static/chunks/0fjlk3~at3w55.js",
      ".next/static/chunks/14s.rtfgouzu..js",
      ".next/static/chunks/turbopack-05vf~d5vj8vz_.js"
    ]
  },
  {
    "route": "/workspace/[category]",
    "firstLoadUncompressedJsBytes": 780719,
    "firstLoadChunkPaths": [
      ".next/static/chunks/1658s.jmfu3bl.js",
      ".next/static/chunks/0~xsfa46ru.-w.js",
      ".next/static/chunks/0np3x1bhafkg4.js",
      ".next/static/chunks/0_t7vr6-missb.js",
      ".next/static/chunks/0a3nm8r6kmyn3.js",
      ".next/static/chunks/0jvyaixqsz1ap.js",
      ".next/static/chunks/0fjlk3~at3w55.js",
      ".next/static/chunks/14s.rtfgouzu..js",
      ".next/static/chunks/turbopack-05vf~d5vj8vz_.js"
    ]
  },
  {
    "route": "/customers",
    "firstLoadUncompressedJsBytes": 775660,
    "firstLoadChunkPaths": [
      ".next/static/chunks/1658s.jmfu3bl.js",
      ".next/static/chunks/0~xsfa46ru.-w.js",
      ".next/static/chunks/0c1f8dk1r3ms~.js",
      ".next/static/chunks/0_t7vr6-missb.js",
      ".next/static/chunks/0a3nm8r6kmyn3.js",
      ".next/static/chunks/0jvyaixqsz1ap.js",
      ".next/static/chunks/0fjlk3~at3w55.js",
      ".next/static/chunks/14s.rtfgouzu..js",
      ".next/static/chunks/turbopack-05vf~d5vj8vz_.js"
    ]
  },
  {
    "route": "/calendar",
    "firstLoadUncompressedJsBytes": 774954,
    "firstLoadChunkPaths": [
      ".next/static/chunks/1658s.jmfu3bl.js",
      ".next/static/chunks/0~xsfa46ru.-w.js",
      ".next/static/chunks/0e02ej.9rjsj2.js",
      ".next/static/chunks/0_t7vr6-missb.js",
      ".next/static/chunks/0a3nm8r6kmyn3.js",
      ".next/static/chunks/0jvyaixqsz1ap.js",
      ".next/static/chunks/0fjlk3~at3w55.js",
      ".next/static/chunks/14s.rtfgouzu..js",
      ".next/static/chunks/turbopack-05vf~d5vj8vz_.js"
    ]
  },
  {
    "route": "/alerts",
    "firstLoadUncompressedJsBytes": 771952,
    "firstLoadChunkPaths": [
      ".next/static/chunks/1658s.jmfu3bl.js",
      ".next/static/chunks/0~xsfa46ru.-w.js",
      ".next/static/chunks/0vi8pq.g.qypj.js",
      ".next/static/chunks/0_t7vr6-missb.js",
      ".next/static/chunks/0a3nm8r6kmyn3.js",
      ".next/static/chunks/0jvyaixqsz1ap.js",
      ".next/static/chunks/0fjlk3~at3w55.js",
      ".next/static/chunks/14s.rtfgouzu..js",
      ".next/static/chunks/turbopack-05vf~d5vj8vz_.js"
    ]
  },
  {
    "route": "/tasks",
    "firstLoadUncompressedJsBytes": 755790,
    "firstLoadChunkPaths": [
      ".next/static/chunks/1658s.jmfu3bl.js",
      ".next/static/chunks/0~xsfa46ru.-w.js",
      ".next/static/chunks/01h27kt34c8p3.js",
      ".next/static/chunks/0_t7vr6-missb.js",
      ".next/static/chunks/0a3nm8r6kmyn3.js",
      ".next/static/chunks/0jvyaixqsz1ap.js",
      ".next/static/chunks/0fjlk3~at3w55.js",
      ".next/static/chunks/14s.rtfgouzu..js",
      ".next/static/chunks/turbopack-05vf~d5vj8vz_.js"
    ]
  },
  {
    "route": "/settings",
    "firstLoadUncompressedJsBytes": 530896,
    "firstLoadChunkPaths": [
      ".next/static/chunks/1658s.jmfu3bl.js",
      ".next/static/chunks/0~xsfa46ru.-w.js",
      ".next/static/chunks/07gnlc5.534ca.js",
      ".next/static/chunks/0a3nm8r6kmyn3.js",
      ".next/static/chunks/0jvyaixqsz1ap.js",
      ".next/static/chunks/0fjlk3~at3w55.js",
      ".next/static/chunks/14s.rtfgouzu..js",
      ".next/static/chunks/turbopack-05vf~d5vj8vz_.js"
    ]
  },
  {
    "route": "/_not-found",
    "firstLoadUncompressedJsBytes": 514646,
    "firstLoadChunkPaths": [
      ".next/static/chunks/1658s.jmfu3bl.js",
      ".next/static/chunks/0~xsfa46ru.-w.js",
      ".next/static/chunks/0a3nm8r6kmyn3.js",
      ".next/static/chunks/0jvyaixqsz1ap.js",
      ".next/static/chunks/0fjlk3~at3w55.js",
      ".next/static/chunks/14s.rtfgouzu..js",
      ".next/static/chunks/turbopack-05vf~d5vj8vz_.js"
    ]
  }
]